LICENSE
README.md
setup.py
listorm/__init__.py
listorm/exceptions.py
listorm.egg-info/PKG-INFO
listorm.egg-info/SOURCES.txt
listorm.egg-info/dependency_links.txt
listorm.egg-info/requires.txt
listorm.egg-info/top_level.txt
listorm/api/__init__.py
listorm/api/helper.py
listorm/api/records.py
listorm/api/row.py
listorm/api/extensions/__init__.py
listorm/api/extensions/csv.py
listorm/api/extensions/excel.py
listorm/api/extensions/io.py
listorm/core/__init__.py
listorm/core/base.py
listorm/core/orm.py
listorm/core/shortcuts.py
listorm/core/utlility.py
listorm/utils/__init__.py
listorm/utils/argtools.py
listorm/utils/etc.py
listorm/utils/excel.py
listorm/utils/plural.py