Metadata-Version: 2.1
Name: listorm
Version: 1.2.4
Summary: list orm methods and shortcuts for table type of dict-list
Home-page: https://github.com/zwolf21/listorm
Author: HS Moon
Author-email: pbr112@naver.com
License: MIT
Keywords: listorm,list of dict,dict list,records,sql,orm
Platform: UNKNOWN
Classifier: Operating System :: OS Independent
Classifier: Programming Language :: Python :: 3.8
Classifier: Programming Language :: Python :: 3.9
Classifier: Programming Language :: Python :: 3.10
Requires-Python: >=3.8
License-File: LICENSE
